docstr_coverage/__init__.py
docstr_coverage/badge.py
docstr_coverage/cli.py
docstr_coverage/config_file.py
docstr_coverage/coverage.py
docstr_coverage/ignore_config.py
docstr_coverage/printers.py
docstr_coverage/result_collection.py
docstr_coverage/visitor.py
docstr_coverage/templates/flat.svg
docstr_coverage-2.3.2.dist-info/LICENSE.txt
docstr_coverage-2.3.2.dist-info/METADATA
docstr_coverage-2.3.2.dist-info/WHEEL
docstr_coverage-2.3.2.dist-info/entry_points.txt
docstr_coverage-2.3.2.dist-info/top_level.txt
docstr_coverage-2.3.2.dist-info/RECORD
