Metadata-Version: 2.1
Name: docstr-coverage
Version: 2.3.2
Summary: Utility for examining python source files to ensure proper documentation. Lists missing docstrings, and calculates overall docstring coverage percentage rating.
Home-page: https://github.com/HunterMcGushion/docstr_coverage
Author: Hunter McGushion
Author-email: hunter@mcgushion.com
License: MIT
Keywords: docstring coverage documentation audit source code statistics report
Platform: UNKNOWN
Classifier: Programming Language :: Python :: 3
Classifier: Programming Language :: Python :: 3.8
Classifier: Programming Language :: Python :: 3.9
Classifier: Programming Language :: Python :: 3.10
Classifier: Programming Language :: Python :: 3.11
Classifier: Programming Language :: Python :: 3.12
Classifier: License :: OSI Approved :: MIT License
Classifier: Operating System :: OS Independent
Classifier: Topic :: Documentation
Classifier: Topic :: Documentation :: Sphinx
Classifier: Topic :: Software Development
Classifier: Topic :: Software Development :: Documentation
Classifier: Topic :: Software Development :: Libraries :: Python Modules
Classifier: Topic :: Software Development :: Quality Assurance
Classifier: Topic :: Utilities
License-File: LICENSE.txt
Requires-Dist: click
Requires-Dist: PyYAML
Requires-Dist: tqdm
Requires-Dist: importlib-resources ; python_version < "3.9"
Provides-Extra: lint
Requires-Dist: flake8 (==4.0.1) ; extra == 'lint'
Requires-Dist: black (==22.3.0) ; extra == 'lint'
Requires-Dist: isort (==5.10.1) ; extra == 'lint'
Provides-Extra: test
Requires-Dist: pytest (==6.2.5) ; extra == 'test'
Requires-Dist: pytest-mock (==3.4.0) ; extra == 'test'
